[
    {
        "hasStock": 1,
        "marketPrice": 189.0,
        "productId": 27,
        "salePrice": 139.0,
        "canUseFullReduction": 1,
        "sort": 59909732,
        "type": 1,
        "productName": "飞科剃须刀-FS371",
        "isShowShoppingCart": false,
        "supportEbuy": 1,
        "productOverview": "",
        "isNewProduct": 0,
        "isShowProductOverview": false,
        "showPic": "http://img.yesm.cn/shopProduct/20180905/20180905114738_573.jpg",
        "labelImg": "http://img.yesm.cn/shopLabel/20191016174526_285.png",
        "canUseCoupon": 0,
        "skuId": 74
    },
    {
        "hasStock": 1,
        "marketPrice": 79.0,
        "productId": 1116,
        "salePrice": 78.0,
        "canUseFullReduction": 1,
        "sort": 59889686,
        "type": 1,
        "productName": "【2.8kg超值免邮】汰渍焕彩护衣洗衣液700克*4瓶",
        "isShowShoppingCart": false,
        "supportEbuy": 1,
        "productOverview": "",
        "isNewProduct": 1,
        "isShowProductOverview": false,
        "showPic": "http://img.yesm.cn/shopProduct/20190606/20190606101229_462.jpg",
        "labelImg": "http://img.yesm.cn/shopLabel/20191017090728_556.png",
        "canUseCoupon": 0,
        "skuId": 1489
    },
    {
        "hasStock": 1,
        "marketPrice": 159.0,
        "productId": 322,
        "salePrice": 149.0,
        "canUseFullReduction": 1,
        "sort": 59862956,
        "type": 1,
        "productName": "Midea/美的多用锅可煎烤 电火锅电煮锅电热锅电砂锅3.5升容量 分体式设计-HS136B",
        "isShowShoppingCart": false,
        "supportEbuy": 1,
        "productOverview": "",
        "isNewProduct": 1,
        "isShowProductOverview": false,
        "showPic": "http://img.yesm.cn/shopProduct/20181119/20181119105835_288.jpg",
        "labelImg": "http://img.yesm.cn/shopLabel/20191016174526_285.png",
        "canUseCoupon": 0,
        "skuId": 605
    },
    {
        "hasStock": 1,
        "marketPrice": 29.0,
        "productId": 805,
        "salePrice": 28.0,
        "canUseFullReduction": 0,
        "sort": 59865874,
        "type": 1,
        "productName": "固特异盲点镜-GY-2231",
        "isShowShoppingCart": false,
        "supportEbuy": 1,
        "productOverview": "",
        "isNewProduct": 1,
        "isShowProductOverview": false,
        "showPic": "http://img.yesm.cn/shopProduct/20181123/20181123165142_966.jpg",
        "canUseCoupon": 0,
        "skuId": 1088
    },
    {
        "hasStock": 1,
        "marketPrice": 49.0,
        "productId": 933,
        "salePrice": 48.0,
        "canUseFullReduction": 1,
        "sort": 59842498,
        "type": 1,
        "productName": "爱丽新 KEKE 防水划痕修复布（1块，颜色随机）",
        "isShowShoppingCart": false,
        "supportEbuy": 1,
        "productOverview": "",
        "isNewProduct": 1,
        "isShowProductOverview": false,
        "showPic": "http://img.yesm.cn/shopProduct/20190221/20190221171249_820.jpg",
        "labelImg": "http://img.yesm.cn/shopLabel/20191016180630_694.png",
        "canUseCoupon": 0,
        "skuId": 1282
    },
    {
        "hasStock": 1,
        "marketPrice": 48.0,
        "productId": 141,
        "salePrice": 38.0,
        "canUseFullReduction": 1,
        "sort": 59853249,
        "type": 1,
        "productName": "磁性手机支架金色",
        "isShowShoppingCart": false,
        "supportEbuy": 1,
        "productOverview": "",
        "isNewProduct": 1,
        "isShowProductOverview": false,
        "showPic": "http://img.yesm.cn/shopProduct/20180904/20180904144112_499.jpg",
        "labelImg": "http://img.yesm.cn/shopLabel/20191016180630_694.png",
        "canUseCoupon": 0,
        "skuId": 424
    },
    {
        "hasStock": 1,
        "marketPrice": 118.0,
        "productId": 763,
        "salePrice": 98.0,
        "canUseFullReduction": 1,
        "sort": 59841491,
        "type": 1,
        "productName": "【飓风吸力，专业电机】变形金刚车载吸尘器TFLP-XC05",
        "isShowShoppingCart": false,
        "supportEbuy": 1,
        "productOverview": "",
        "isNewProduct": 1,
        "isShowProductOverview": false,
        "showPic": "http://img.yesm.cn/shopProduct/20180926/20180926162638_667.jpg",
        "labelImg": "http://img.yesm.cn/shopLabel/20191016180630_694.png",
        "canUseCoupon": 0,
        "skuId": 1046
    },
    {
        "hasStock": 1,
        "marketPrice": 120.0,
        "productId": 132,
        "salePrice": 66.0,
        "canUseFullReduction": 1,
        "sort": 59836351,
        "type": 1,
        "productName": "【任它狂风暴雨，我有反向伞】免持式反向伞--蓝色",
        "isShowShoppingCart": false,
        "supportEbuy": 1,
        "productOverview": "",
        "isNewProduct": 1,
        "isShowProductOverview": false,
        "showPic": "http://img.yesm.cn/shopProduct/20190418/20190418171451_979.jpg",
        "labelImg": "http://img.yesm.cn/shopLabel/20191016180630_694.png",
        "canUseCoupon": 0,
        "skuId": 409
    },
    {
        "hasStock": 1,
        "marketPrice": 369.0,
        "productId": 545,
        "salePrice": 359.0,
        "canUseFullReduction": 1,
        "sort": 59835681,
        "type": 1,
        "productName": "【微压米饭·口感该更佳】Midea/美的电压力锅电饭锅PCS5011HM一锅双胆 智能12小时预约5升高压锅美的电饭煲",
        "isShowShoppingCart": false,
        "supportEbuy": 1,
        "productOverview": "",
        "isNewProduct": 1,
        "isShowProductOverview": false,
        "showPic": "http://img.yesm.cn/shopProduct/20180622/20180622183145_530.jpg",
        "labelImg": "http://img.yesm.cn/shopLabel/20191016174627_460.png",
        "canUseCoupon": 0,
        "skuId": 828
    },
    {
        "hasStock": 1,
        "marketPrice": 120.0,
        "productId": 132,
        "salePrice": 66.0,
        "canUseFullReduction": 1,
        "sort": 59788369,
        "type": 1,
        "productName": "【任它狂风暴雨，我有反向伞】免持式汽车反向伞--红色",
        "isShowShoppingCart": false,
        "supportEbuy": 1,
        "productOverview": "",
        "isNewProduct": 1,
        "isShowProductOverview": false,
        "showPic": "http://img.yesm.cn/shopProduct/20190418/20190418171501_319.jpg",
        "labelImg": "http://img.yesm.cn/shopLabel/20191016180630_694.png",
        "canUseCoupon": 0,
        "skuId": 410
    },
    {
        "hasStock": 1,
        "marketPrice": 269.0,
        "productId": 543,
        "salePrice": 236.0,
        "canUseFullReduction": 1,
        "sort": 59806810,
        "type": 1,
        "productName": "Midea/美的电磁炉HT2117HM多功能防水触摸屏超薄 家用2100W",
        "isShowShoppingCart": false,
        "supportEbuy": 1,
        "productOverview": "",
        "isNewProduct": 1,
        "isShowProductOverview": false,
        "showPic": "http://img.yesm.cn/shopProduct/20180622/20180622182548_61.jpg",
        "labelImg": "http://img.yesm.cn/shopLabel/20191016174526_285.png",
        "canUseCoupon": 0,
        "skuId": 826
    },
    {
        "hasStock": 1,
        "marketPrice": 99.0,
        "productId": 281,
        "salePrice": 48.0,
        "canUseFullReduction": 1,
        "sort": 59815276,
        "type": 1,
        "productName": "丸美日夜精华眼霜3g+3g",
        "isShowShoppingCart": false,
        "supportEbuy": 1,
        "productOverview": "",
        "isNewProduct": 1,
        "isShowProductOverview": false,
        "showPic": "http://img.yesm.cn/shopProduct/20180514/20180514181410_752.jpg",
        "labelImg": "http://img.yesm.cn/shopLabel/20191016173930_203.png",
        "canUseCoupon": 0,
        "skuId": 564
    },
    {
        "hasStock": 0,
        "marketPrice": 99.0,
        "productId": 31,
        "salePrice": 59.0,
        "canUseFullReduction": 1,
        "sort": 59797863,
        "type": 1,
        "productName": "声波电动牙刷H3（欧丽白）",
        "isShowShoppingCart": false,
        "supportEbuy": 1,
        "productOverview": "",
        "isNewProduct": 0,
        "isShowProductOverview": false,
        "showPic": "http://img.yesm.cn/shopProduct/20190322/20190322143607_985.png",
        "labelImg": "http://img.yesm.cn/shopLabel/20191016173930_203.png",
        "canUseCoupon": 0,
        "skuId": 83
    },
    {
        "hasStock": 0,
        "marketPrice": 189.0,
        "productId": 4,
        "salePrice": 158.0,
        "canUseFullReduction": 0,
        "sort": 59773364,
        "type": 1,
        "productName": "【低噪柔风】钻石牌机械电风扇落地扇风扇FS-40IIF（黑色）",
        "isShowShoppingCart": false,
        "supportEbuy": 1,
        "productOverview": "",
        "isNewProduct": 1,
        "isShowProductOverview": false,
        "showPic": "http://img.yesm.cn/shopProduct/20180627/20180627100229_845.jpg",
        "canUseCoupon": 0,
        "skuId": 12
    },
    {
        "hasStock": 1,
        "marketPrice": 79.0,
        "productId": 295,
        "salePrice": 32.0,
        "canUseFullReduction": 0,
        "sort": 59826106,
        "type": 1,
        "productName": "【加粗铜芯、充电提速】唐士顿编织三合一数据线",
        "isShowShoppingCart": false,
        "supportEbuy": 1,
        "productOverview": "支持TYPE-C、苹果、安卓",
        "isNewProduct": 1,
        "isShowProductOverview": true,
        "showPic": "http://img.yesm.cn/shopProduct/20190531/20190531094240_707.jpg",
        "canUseCoupon": 0,
        "skuId": 578
    },
    {
        "hasStock": 1,
        "marketPrice": 99.0,
        "productId": 37,
        "salePrice": 89.0,
        "canUseFullReduction": 1,
        "sort": 59783416,
        "type": 1,
        "productName": "啄木鸟商务自动扣皮带GD1857-AX黑色",
        "isShowShoppingCart": false,
        "supportEbuy": 1,
        "productOverview": "",
        "isNewProduct": 0,
        "isShowProductOverview": false,
        "showPic": "http://img.yesm.cn/shopProduct/20190612/20190612163408_451.jpg",
        "labelImg": "http://img.yesm.cn/shopLabel/20191016173930_203.png",
        "canUseCoupon": 0,
        "skuId": 106
    },
    {
        "hasStock": 1,
        "marketPrice": 88.0,
        "productId": 893,
        "salePrice": 68.0,
        "canUseFullReduction": 1,
        "sort": 59776836,
        "type": 1,
        "productName": "澳雪梦幻海马香水沐浴露",
        "isShowShoppingCart": false,
        "supportEbuy": 1,
        "productOverview": "",
        "isNewProduct": 1,
        "isShowProductOverview": false,
        "showPic": "http://img.yesm.cn/shopProduct/20181229/20181229175120_206.jpg",
        "labelImg": "http://img.yesm.cn/shopLabel/20191016173930_203.png",
        "canUseCoupon": 0,
        "skuId": 1227
    },
    {
        "hasStock": 1,
        "marketPrice": 158.0,
        "productId": 732,
        "salePrice": 129.0,
        "canUseFullReduction": 1,
        "sort": 59721110,
        "type": 1,
        "productName": "松下电吹风-EH-ND21",
        "isShowShoppingCart": false,
        "supportEbuy": 1,
        "productOverview": "",
        "isNewProduct": 1,
        "isShowProductOverview": false,
        "showPic": "http://img.yesm.cn/shopProduct/20181009/20181009165440_818.jpg",
        "labelImg": "http://img.yesm.cn/shopLabel/20191016173930_203.png",
        "canUseCoupon": 0,
        "skuId": 1015
    },
    {
        "hasStock": 1,
        "marketPrice": 259.0,
        "productId": 318,
        "salePrice": 219.0,
        "canUseFullReduction": 1,
        "sort": 59754594,
        "type": 1,
        "productName": "Midea/美的电饭煲FS4018D锅家用4升预约电饭锅3-4-5-6人",
        "isShowShoppingCart": false,
        "supportEbuy": 1,
        "productOverview": "",
        "isNewProduct": 1,
        "isShowProductOverview": false,
        "showPic": "http://img.yesm.cn/shopProduct/20180605/20180605092712_432.jpg",
        "labelImg": "http://img.yesm.cn/shopLabel/20191016174526_285.png",
        "canUseCoupon": 0,
        "skuId": 601
    },
    {
        "hasStock": 1,
        "marketPrice": 499.0,
        "productId": 32,
        "salePrice": 99.0,
        "canUseFullReduction": 1,
        "sort": 59768777,
        "type": 1,
        "productName": "瑞动双肩包背包电脑包商务背包-MT-5918-14T00",
        "isShowShoppingCart": false,
        "supportEbuy": 1,
        "productOverview": "",
        "isNewProduct": 0,
        "isShowProductOverview": false,
        "showPic": "http://img.yesm.cn/shopProduct/20180821/20180821100404_518.jpg",
        "labelImg": "http://img.yesm.cn/shopLabel/20191016173930_203.png",
        "canUseCoupon": 0,
        "skuId": 86
    }
]
